quickhost/Cli.py
quickhost/QuickhostPlugin.py
quickhost/__init__.py
quickhost/constants.py
quickhost/quickhost_app_base.py
quickhost/temp_data_collector.py
quickhost/utilities.py
scripts/main.py
quickhost-0.2.0.dist-info/LICENSE.txt
quickhost-0.2.0.dist-info/METADATA
quickhost-0.2.0.dist-info/WHEEL
quickhost-0.2.0.dist-info/entry_points.txt
quickhost-0.2.0.dist-info/top_level.txt
quickhost-0.2.0.dist-info/RECORD
