Metadata-Version: 2.1
Name: quickhost
Version: 0.2.0
Summary: Start a publically available webhost, quickly.
Author-email: zeebrow <zeebrow@zeebrow.io>
Project-URL: Homepage, https://github.com/zeebrow/quickhost
Project-URL: Issues, https://github.com/zeebrow/quickhost/issues
Classifier: Programming Language :: Python :: 3
Classifier: License :: OSI Approved :: MIT License
Classifier: Operating System :: OS Independent
Requires-Python: >=3.8
License-File: LICENSE.txt
